coffeece/Excel.py
coffeece/Popup.py
coffeece/SQLiteDB.py
coffeece/System.py
coffeece/__init__.py
coffeece/scripts/__init__.py
coffeece/scripts/venv_cleaner.py
coffeece-1.1.0.dist-info/LICENSE
coffeece-1.1.0.dist-info/METADATA
coffeece-1.1.0.dist-info/WHEEL
coffeece-1.1.0.dist-info/top_level.txt
coffeece-1.1.0.dist-info/RECORD
