Metadata-Version: 2.1
Name: coffeece
Version: 1.1.0
Summary: Python useful classes for office work automation
Home-page: https://github.com/FARBEX97/coffeece
Author: FARBEX97
Author-email: fernandoarbexcv@gmail.com
License: UNKNOWN
Platform: UNKNOWN
Classifier: Programming Language :: Python :: 3
Classifier: License :: OSI Approved :: MIT License
Classifier: Operating System :: OS Independent
Requires-Python: >=3.6
